pymock_api/__init__.py
pymock_api/__main__.py
pymock_api/__pkg_info__.py
pymock_api/_utils/__init__.py
pymock_api/_utils/api_client.py
pymock_api/_utils/file_opt.py
pymock_api/_utils/importing.py
pymock_api/command/__init__.py
pymock_api/command/_common/__init__.py
pymock_api/command/_common/component.py
pymock_api/command/add/__init__.py
pymock_api/command/add/component.py
pymock_api/command/check/__init__.py
pymock_api/command/check/component.py
pymock_api/command/component.py
pymock_api/command/get/__init__.py
pymock_api/command/get/component.py
pymock_api/command/options.py
pymock_api/command/process.py
pymock_api/command/pull/__init__.py
pymock_api/command/pull/component.py
pymock_api/command/run/__init__.py
pymock_api/command/run/component.py
pymock_api/command/sample/__init__.py
pymock_api/command/sample/component.py
pymock_api/exceptions.py
pymock_api/model/__init__.py
pymock_api/model/_sample.py
pymock_api/model/api_config/__init__.py
pymock_api/model/api_config/_base.py
pymock_api/model/api_config/apis/__init__.py
pymock_api/model/api_config/apis/_property.py
pymock_api/model/api_config/apis/request.py
pymock_api/model/api_config/apis/response.py
pymock_api/model/api_config/base.py
pymock_api/model/api_config/item.py
pymock_api/model/api_config/template/__init__.py
pymock_api/model/api_config/template/_base.py
pymock_api/model/api_config/template/_base_wrapper.py
pymock_api/model/api_config/template/_divide.py
pymock_api/model/api_config/template/_load.py
pymock_api/model/cmd_args.py
pymock_api/model/enums.py
pymock_api/model/openapi/__init__.py
pymock_api/model/openapi/_base.py
pymock_api/model/openapi/_js_handlers.py
pymock_api/model/openapi/_parser.py
pymock_api/model/openapi/_parser_factory.py
pymock_api/model/openapi/_schema_parser.py
pymock_api/model/openapi/config.py
pymock_api/runner.py
pymock_api/server/__init__.py
pymock_api/server/application/__init__.py
pymock_api/server/application/code_generator.py
pymock_api/server/application/process.py
pymock_api-0.2.0.dist-info/LICENSE
pymock_api-0.2.0.dist-info/METADATA
pymock_api-0.2.0.dist-info/WHEEL
pymock_api-0.2.0.dist-info/entry_points.txt
pymock_api-0.2.0.dist-info/RECORD
