Metadata-Version: 2.1
Name: PyMock-API
Version: 0.2.0
Summary: 🕸🤖👺 A Python tool to mock API easily and humanly without any coding.
Home-page: https://github.com/Chisanan232/PyMock-API
License: MIT
Keywords: mock,API,mock API,web,server
Author: Liu, Bryant
Author-email: chi10211201@cycu.org.tw
Requires-Python: >=3.8,<4.0
Classifier: Development Status :: 3 - Alpha
Classifier: Environment :: Console
Classifier: Intended Audience :: Developers
Classifier: License :: OSI Approved :: MIT License
Classifier: Operating System :: OS Independent
Classifier: Programming Language :: Python :: 3
Classifier: Programming Language :: Python :: 3.8
Classifier: Programming Language :: Python :: 3.9
Classifier: Programming Language :: Python :: 3.10
Classifier: Programming Language :: Python :: 3.11
Classifier: Programming Language :: Python :: 3.12
Classifier: Programming Language :: Python :: 3.13
Classifier: Topic :: Internet
Classifier: Topic :: Internet :: WWW/HTTP
Classifier: Topic :: Internet :: WWW/HTTP :: Dynamic Content
Classifier: Topic :: Internet :: WWW/HTTP :: HTTP Servers
Classifier: Topic :: Software Development :: Libraries :: Python Modules
Classifier: Topic :: Software Development :: Testing :: Mocking
Classifier: Topic :: Utilities
Requires-Dist: Flask[all,flask] (>=3.0.2,<4.0.0)
Requires-Dist: PyYAML (>=6.0,<7.0)
Requires-Dist: fastapi[all,fastapi] (>=0.110,<0.116)
Requires-Dist: gunicorn[all,flask] (>=21.2,<24.0)
Requires-Dist: uvicorn[all,fastapi] (>=0.29,<0.33)
Project-URL: Documentation, https://chisanan232.github.io/PyMock-API/
